LICENSE
MANIFEST.in
README.md
setup.py
src/OMS.cc
src/OMS.h
src/area_and_volume.cc
src/area_and_volume.h
src/arguments.h
src/channel.cc
src/channel.h
src/cluster.cc
src/cluster.h
src/cycle.cc
src/cycle.h
src/feature.h
src/general.h
src/geometry.cc
src/geometry.h
src/gpu_energy.h
src/graphstorage.cc
src/graphstorage.h
src/grid.cc
src/grid.h
src/heap.h
src/holo_similarity.h
src/holograms.h
src/instructions.h
src/material.cc
src/material.h
src/mindist.cc
src/mindist.h
src/net.cc
src/net.h
src/network.cc
src/network.h
src/networkaccessibility.cc
src/networkaccessibility.h
src/networkanalysis.cc
src/networkanalysis.h
src/networkinfo.cc
src/networkinfo.h
src/networkio.cc
src/networkio.h
src/networkstorage.cc
src/networkstorage.h
src/poreinfo.h
src/psd.cc
src/psd.h
src/ray.cc
src/ray.h
src/rmsd.cc
src/rmsd.h
src/segment.h
src/sphere_approx.cc
src/sphere_approx.h
src/string_additions.cc
src/string_additions.h
src/symbcalc.cc
src/symbcalc.h
src/symmetry.cc
src/symmetry.h
src/v_network.cc
src/v_network.h
src/voronoicell.cc
src/voronoicell.h
src/zeo_consts.h
src/zeojobs.h
src/Eigen/src/Cholesky/LDLT.h
src/Eigen/src/Cholesky/LLT.h
src/Eigen/src/Cholesky/LLT_MKL.h
src/Eigen/src/CholmodSupport/CholmodSupport.h
src/Eigen/src/Core/Array.h
src/Eigen/src/Core/ArrayBase.h
src/Eigen/src/Core/ArrayWrapper.h
src/Eigen/src/Core/Assign.h
src/Eigen/src/Core/Assign_MKL.h
src/Eigen/src/Core/BandMatrix.h
src/Eigen/src/Core/Block.h
src/Eigen/src/Core/BooleanRedux.h
src/Eigen/src/Core/CommaInitializer.h
src/Eigen/src/Core/CoreIterators.h
src/Eigen/src/Core/CwiseBinaryOp.h
src/Eigen/src/Core/CwiseNullaryOp.h
src/Eigen/src/Core/CwiseUnaryOp.h
src/Eigen/src/Core/CwiseUnaryView.h
src/Eigen/src/Core/DenseBase.h
src/Eigen/src/Core/DenseCoeffsBase.h
src/Eigen/src/Core/DenseStorage.h
src/Eigen/src/Core/Diagonal.h
src/Eigen/src/Core/DiagonalMatrix.h
src/Eigen/src/Core/DiagonalProduct.h
src/Eigen/src/Core/Dot.h
src/Eigen/src/Core/EigenBase.h
src/Eigen/src/Core/Flagged.h
src/zeoplusplus.egg-info/PKG-INFO
src/zeoplusplus.egg-info/SOURCES.txt
src/zeoplusplus.egg-info/dependency_links.txt
src/zeoplusplus.egg-info/not-zip-safe
src/zeoplusplus.egg-info/top_level.txt